LICENCE.txt
MANIFEST.in
README.md
pyproject.toml
setup.cfg
setup.py
onecall/__init__.py
onecall/binance.py
onecall/binance_spot.py
onecall/bybit.py
onecall/ftx.py
onecall/ftx_us.py
onecall/kucoin.py
onecall/phemex.py
onecall/test.py
onecall.egg-info/PKG-INFO
onecall.egg-info/SOURCES.txt
onecall.egg-info/dependency_links.txt
onecall.egg-info/requires.txt
onecall.egg-info/top_level.txt
onecall/base/__init__.py
onecall/base/exceptions.py
onecall/base/exchange.py
onecall/base/urls.py
onecall/base/utils.py