Metadata-Version: 2.1
Name: onecall
Version: 1.0.12
Summary: An algorithmic trading python package to save thousands of hours with the quickest crypto trading library so you can easily algo trade on any exchange & execute with unified function calls
Home-page: https://github.com/moondevonyt/onecall
Author: Moon Dev
Author-email: moondevonyt@gmail.com
Keywords: python,onecall,trading bot,quant,trading,trading algo,algorithmic trading,algo trading,crypto,exchange,automate trading,pinescript,mev,crypto exchange,binance,ftx,ethereum,solana,bitcoin,coinbase,phemex,bybit
Classifier: Development Status :: 3 - Alpha
Classifier: Intended Audience :: Developers
Classifier: Intended Audience :: Financial and Insurance Industry
Classifier: Intended Audience :: Information Technology
Classifier: Programming Language :: Python :: 2
Classifier: Programming Language :: Python :: 3
Classifier: Operating System :: MacOS :: MacOS X
Classifier: Operating System :: Microsoft :: Windows
Requires-Python: >=3.7
License-File: LICENCE.txt
